pwnatlas/__init__.py
pwnatlas/get.py
pwnatlas/util/__init__.py
pwnatlas/util/exploitdb.py
pwnatlas/util/parse_json.py
PwnAtlas-0.1b2.dist-info/LICENSE
PwnAtlas-0.1b2.dist-info/METADATA
PwnAtlas-0.1b2.dist-info/WHEEL
PwnAtlas-0.1b2.dist-info/top_level.txt
PwnAtlas-0.1b2.dist-info/RECORD
