Metadata-Version: 2.1
Name: PwnAtlas
Version: 0.1b2
Summary: CVE and ExploitDB Search Tool
Home-page: https://github.com/CougarCS-InfoSec/PwnAtlas
Author: Diante J.
Author-email: diante.jackson@proton.me
License-File: LICENSE
Requires-Dist: requests
Requires-Dist: bs4
